StreamDiffusionIO/__init__.py
StreamDiffusionIO/pipelines/__init__.py
StreamDiffusionIO/pipelines/lcm_text2img.py
StreamDiffusionIO/pipelines/ldm_text2img.py
StreamDiffusionIO-0.0.3.dist-info/LICENSE
StreamDiffusionIO-0.0.3.dist-info/METADATA
StreamDiffusionIO-0.0.3.dist-info/WHEEL
StreamDiffusionIO-0.0.3.dist-info/top_level.txt
StreamDiffusionIO-0.0.3.dist-info/RECORD
