Metadata-Version: 2.1
Name: StreamDiffusionIO
Version: 0.0.3
Summary: A lightweight pipeline using StreamDiffusion, aimming to support streaming IO operations.
Author-email: "Yihao (Ethan) Wang" <yihao.w@nyu.edu>
License: Apache License
Project-URL: Repository, https://github.com/AgainstEntropy/StreamDiffusionIO.git
Keywords: DeepLearning,StableDiffusion,diffusion,stream,PyTorch
Classifier: Development Status :: 3 - Alpha
Classifier: Intended Audience :: Developers
Classifier: License :: OSI Approved :: MIT License
Classifier: Programming Language :: Python :: 3
Classifier: Programming Language :: Python :: 3.10
Requires-Python: >=3.10
License-File: LICENSE
Requires-Dist: torch
Requires-Dist: diffusers
Requires-Dist: transformers
Provides-Extra: xformers
Requires-Dist: xformers ; extra == 'xformers'
